sanskrit_parser/__init__.py
sanskrit_parser/api.py
sanskrit_parser/cmd_line.py
sanskrit_parser/base/__init__.py
sanskrit_parser/base/maheshvara_sutra.py
sanskrit_parser/base/sanskrit_base.py
sanskrit_parser/data/dhAtu-pATha-kRShNAchArya.json
sanskrit_parser/data/inria_forms_pos.db
sanskrit_parser/data/inria_stems_tags_buf.pkl
sanskrit_parser/data/sandhi_rules.zip
sanskrit_parser/data/sanskrit_data.db
sanskrit_parser/data/sentencepiece.model
sanskrit_parser/data/word2vec_model.dat
sanskrit_parser/generator/__init__.py
sanskrit_parser/generator/cmd_line.py
sanskrit_parser/generator/dhatu.py
sanskrit_parser/generator/generator.py
sanskrit_parser/generator/maheshvara.py
sanskrit_parser/generator/operations.py
sanskrit_parser/generator/paninian_object.py
sanskrit_parser/generator/paribhasha.py
sanskrit_parser/generator/prakriya.py
sanskrit_parser/generator/pratipadika.py
sanskrit_parser/generator/pratyaya.py
sanskrit_parser/generator/process_yaml.py
sanskrit_parser/generator/sutra.py
sanskrit_parser/generator/sutras_yaml.py
sanskrit_parser/output_utils/__init__.py
sanskrit_parser/parser/__init__.py
sanskrit_parser/parser/datastructures.py
sanskrit_parser/parser/sandhi.py
sanskrit_parser/parser/sandhi_analyzer.py
sanskrit_parser/rest_api/__init__.py
sanskrit_parser/rest_api/api_v1.py
sanskrit_parser/rest_api/flask_helper.py
sanskrit_parser/rest_api/run.py
sanskrit_parser/util/DhatuWrapper.py
sanskrit_parser/util/__init__.py
sanskrit_parser/util/data_manager.py
sanskrit_parser/util/disjoint_set.py
sanskrit_parser/util/inriatagmapper.py
sanskrit_parser/util/inriaxmlwrapper.py
sanskrit_parser/util/lexical_lookup.py
sanskrit_parser/util/lexical_lookup_factory.py
sanskrit_parser/util/lexical_scorer.py
sanskrit_parser/util/normalization.py
sanskrit_parser/util/sanskrit_data_wrapper.py
web/__init__.py
web/wsgi_app.py
sanskrit_parser-0.2.6.dist-info/LICENSE
sanskrit_parser-0.2.6.dist-info/METADATA
sanskrit_parser-0.2.6.dist-info/WHEEL
sanskrit_parser-0.2.6.dist-info/entry_points.txt
sanskrit_parser-0.2.6.dist-info/top_level.txt
sanskrit_parser-0.2.6.dist-info/RECORD
