Metadata-Version: 2.1
Name: sanskrit-parser
Version: 0.2.6
Summary: Tools for lexical and morphological analysis of Sanskrit
Home-page: https://github.com/kmadathil/sanskrit_parser
Author: Sanskrit programmers
Author-email: sanskrit-programmers@googlegroups.com
License: MIT
Keywords: sanskrit samskritam
Classifier: Development Status :: 3 - Alpha
Classifier: Intended Audience :: Education
Classifier: Intended Audience :: Science/Research
Classifier: Intended Audience :: Developers
Classifier: Topic :: Text Processing :: Linguistic
Classifier: License :: OSI Approved :: MIT License
Classifier: Programming Language :: Python :: 3
Classifier: Programming Language :: Python :: 3.7
Classifier: Programming Language :: Python :: 3.8
License-File: LICENSE
Requires-Dist: indic-transliteration (!=1.9.5,!=1.9.6)
Requires-Dist: lxml
Requires-Dist: networkx
Requires-Dist: tinydb
Requires-Dist: six
Requires-Dist: flask
Requires-Dist: flask-restx
Requires-Dist: flask-cors
Requires-Dist: jsonpickle
Requires-Dist: sanskrit-util
Requires-Dist: sqlalchemy (>=1.4)
Requires-Dist: pydot
Requires-Dist: pandas
Requires-Dist: xlrd
Requires-Dist: importlib-resources
Requires-Dist: werkzeug (==2.1.2)
